_lovely_jax_hook.pth
_lovely_jax_hook.py
lovely_jax/__init__.py
lovely_jax/_modidx.py
lovely_jax/patch.py
lovely_jax/repr_chans.py
lovely_jax/repr_plt.py
lovely_jax/repr_rgb.py
lovely_jax/repr_str.py
lovely_jax/utils/__init__.py
lovely_jax/utils/config.py
lovely_jax/utils/misc.py
lovely_jax-0.1.4.dist-info/licenses/LICENSE
lovely_jax-0.1.4.dist-info/METADATA
lovely_jax-0.1.4.dist-info/WHEEL
lovely_jax-0.1.4.dist-info/entry_points.txt
lovely_jax-0.1.4.dist-info/top_level.txt
lovely_jax-0.1.4.dist-info/RECORD
